json_to_table/__init__.py
json_to_table/__main__.py
json_to_table/commands.py
json_to_table-0.1.0.dist-info/entry_points.txt
json_to_table-0.1.0.dist-info/WHEEL
json_to_table-0.1.0.dist-info/METADATA
json_to_table-0.1.0.dist-info/RECORD
