Metadata-Version: 2.1
Name: json-to-table
Version: 0.1.0
Summary: Convert Json File to CSV(XLSX)
Home-page: https://github.com/duyixian1234/json2table
License: MIT
Author: duyixian
Author-email: duyixian1234@qq.com
Requires-Python: >=3.9,<4.0
Classifier: License :: OSI Approved :: MIT License
Classifier: Programming Language :: Python :: 3
Classifier: Programming Language :: Python :: 3.10
Classifier: Programming Language :: Python :: 3.9
Requires-Dist: openpyxl (>=3.0.9,<4.0.0)
Requires-Dist: pandas (>=1.3.4,<2.0.0)
Requires-Dist: typer (>=0.4.0,<0.5.0)
Requires-Dist: xlwt (>=1.3.0,<2.0.0)
Project-URL: Repository, https://github.com/duyixian1234/json2table
